{
    "relationships": [
        {
            "relationshipId": 1,
            "relationshipName": "projectConfiguration",
            "relationshipNameCapitalized": "ProjectConfiguration",
            "relationshipFieldName": "projectConfiguration",
            "otherEntityName": "projectConfiguration",
            "relationshipType": "many-to-one",
            "otherEntityNameCapitalized": "ProjectConfiguration",
            "otherEntityField": "name"
        }
    ],
    "fields": [
        {
            "fieldId": 1,
            "fieldName": "type",
            "fieldType": "ReponseTypeEnum",
            "fieldIsEnum": true,
            "fieldValues": "ERROR,INFO",
            "fieldNameCapitalized": "Type",
            "fieldNameUnderscored": "type",
            "fieldValidate": false
        },
        {
            "fieldId": 2,
            "fieldName": "message",
            "fieldType": "String",
            "fieldNameCapitalized": "Message",
            "fieldNameUnderscored": "message",
            "fieldValidate": false
        },
        {
            "fieldId": 3,
            "fieldName": "response",
            "fieldType": "String",
            "fieldNameCapitalized": "Response",
            "fieldNameUnderscored": "response",
            "fieldValidate": false
        },
        {
            "fieldId": 4,
            "fieldName": "code",
            "fieldType": "Integer",
            "fieldNameCapitalized": "Code",
            "fieldNameUnderscored": "code",
            "fieldValidate": false
        },
        {
            "fieldId": 5,
            "fieldName": "duration",
            "fieldType": "Long",
            "fieldNameCapitalized": "Duration",
            "fieldNameUnderscored": "duration",
            "fieldValidate": false
        },
        {
            "fieldId": 8,
            "fieldName": "emailSent",
            "fieldType": "Boolean",
            "fieldNameCapitalized": "EmailSent",
            "fieldNameUnderscored": "email_sent",
            "fieldInJavaBeanMethod": "EmailSent",
            "fieldValidate": false
        },
        {
            "fieldId": 9,
            "fieldName": "date",
            "fieldType": "DateTime",
            "fieldNameCapitalized": "Date",
            "fieldNameUnderscored": "date",
            "fieldInJavaBeanMethod": "Date",
            "fieldValidate": false
        },
        {
            "fieldId": 10,
            "fieldName": "stackTrace",
            "fieldType": "String",
            "fieldNameCapitalized": "StackTrace",
            "fieldNameUnderscored": "stack_trace",
            "fieldInJavaBeanMethod": "StackTrace",
            "fieldValidate": false
        }
    ],
    "fieldsContainOwnerManyToMany": false,
    "fieldsContainOneToMany": false,
    "fieldsContainLocalDate": false,
    "fieldsContainCustomTime": true,
    "fieldsContainBigDecimal": false,
    "fieldsContainDateTime": true,
    "fieldsContainDate": false,
    "changelogDate": "20150314222833",
    "pagination": "infinite-scroll",
    "validation": false
}
